ripperdoc/__init__.py
ripperdoc/__main__.py
ripperdoc/cli/__init__.py
ripperdoc/cli/cli.py
ripperdoc/cli/commands/__init__.py
ripperdoc/cli/commands/agents_cmd.py
ripperdoc/cli/commands/base.py
ripperdoc/cli/commands/clear_cmd.py
ripperdoc/cli/commands/compact_cmd.py
ripperdoc/cli/commands/config_cmd.py
ripperdoc/cli/commands/context_cmd.py
ripperdoc/cli/commands/cost_cmd.py
ripperdoc/cli/commands/doctor_cmd.py
ripperdoc/cli/commands/exit_cmd.py
ripperdoc/cli/commands/help_cmd.py
ripperdoc/cli/commands/hooks_cmd.py
ripperdoc/cli/commands/mcp_cmd.py
ripperdoc/cli/commands/memory_cmd.py
ripperdoc/cli/commands/models_cmd.py
ripperdoc/cli/commands/permissions_cmd.py
ripperdoc/cli/commands/resume_cmd.py
ripperdoc/cli/commands/skills_cmd.py
ripperdoc/cli/commands/stats_cmd.py
ripperdoc/cli/commands/status_cmd.py
ripperdoc/cli/commands/tasks_cmd.py
ripperdoc/cli/commands/themes_cmd.py
ripperdoc/cli/commands/todos_cmd.py
ripperdoc/cli/commands/tools_cmd.py
ripperdoc/cli/ui/__init__.py
ripperdoc/cli/ui/context_display.py
ripperdoc/cli/ui/file_mention_completer.py
ripperdoc/cli/ui/helpers.py
ripperdoc/cli/ui/interrupt_handler.py
ripperdoc/cli/ui/message_display.py
ripperdoc/cli/ui/panels.py
ripperdoc/cli/ui/provider_options.py
ripperdoc/cli/ui/rich_ui.py
ripperdoc/cli/ui/spinner.py
ripperdoc/cli/ui/thinking_spinner.py
ripperdoc/cli/ui/tool_renderers.py
ripperdoc/cli/ui/wizard.py
ripperdoc/core/__init__.py
ripperdoc/core/agents.py
ripperdoc/core/commands.py
ripperdoc/core/config.py
ripperdoc/core/custom_commands.py
ripperdoc/core/default_tools.py
ripperdoc/core/permissions.py
ripperdoc/core/query.py
ripperdoc/core/query_utils.py
ripperdoc/core/skills.py
ripperdoc/core/system_prompt.py
ripperdoc/core/theme.py
ripperdoc/core/tool.py
ripperdoc/core/hooks/__init__.py
ripperdoc/core/hooks/config.py
ripperdoc/core/hooks/events.py
ripperdoc/core/hooks/executor.py
ripperdoc/core/hooks/integration.py
ripperdoc/core/hooks/llm_callback.py
ripperdoc/core/hooks/manager.py
ripperdoc-0.3.0.dist-info/licenses/LICENSE
ripperdoc-0.3.0.dist-info/METADATA
ripperdoc-0.3.0.dist-info/WHEEL
ripperdoc-0.3.0.dist-info/entry_points.txt
ripperdoc-0.3.0.dist-info/top_level.txt
ripperdoc-0.3.0.dist-info/RECORD
