Metadata-Version: 2.4
Name: ripperdoc
Version: 0.3.0
Summary: AI-powered terminal assistant for coding tasks
Author: Ripperdoc Team
License: Apache-2.0
Classifier: Development Status :: 3 - Alpha
Classifier: Intended Audience :: Developers
Classifier: License :: OSI Approved :: Apache Software License
Classifier: Programming Language :: Python :: 3
Classifier: Programming Language :: Python :: 3.10
Classifier: Programming Language :: Python :: 3.11
Classifier: Programming Language :: Python :: 3.12
Requires-Python: >=3.10
License-File: LICENSE
Requires-Dist: anthropic>=0.39.0
Requires-Dist: openai>=1.0.0
Requires-Dist: click>=8.1.0
Requires-Dist: rich>=13.0.0
Requires-Dist: pydantic>=2.0.0
Requires-Dist: python-dotenv>=1.0.0
Requires-Dist: aiofiles>=23.0.0
Requires-Dist: prompt-toolkit>=3.0.0
Requires-Dist: PyYAML>=6.0.0
Requires-Dist: mcp[cli]>=1.25.0
Requires-Dist: json_repair>=0.54.2
Requires-Dist: tiktoken>=0.7.0
Requires-Dist: google-genai>=0.3.0
Requires-Dist: charset-normalizer>=3.0.0
Provides-Extra: dev
Requires-Dist: pytest>=7.0.0; extra == "dev"
Requires-Dist: pytest-asyncio>=0.21.0; extra == "dev"
Requires-Dist: mypy>=1.0.0; extra == "dev"
Requires-Dist: black>=23.0.0; extra == "dev"
Requires-Dist: ruff>=0.1.0; extra == "dev"
Provides-Extra: anthropic
Requires-Dist: anthropic>=0.39.0; extra == "anthropic"
Provides-Extra: openai
Requires-Dist: openai>=1.0.0; extra == "openai"
Provides-Extra: gemini
Requires-Dist: google-genai>=0.3.0; extra == "gemini"
Dynamic: license-file
